<xml>
<datos>
	<ciudad>
		<nombre>La Plata</nombre>
		<personas>
			<persona>
				<nombre>Pedro</nombre>
				<apellido>Sanchez</apellido>
				<edad>23</edad>
			</persona>
			<persona>
				<nombre>Juan</nombre>
				<apellido>Tevez</apellido>
				<edad>23</edad>		
			</persona>
			<persona>
				<nombre>Mario</nombre>
				<apellido>Scala</apellido>
				<edad>23</edad>
			</persona>
		</personas>
	</ciudad>
	<ciudad>
		<nombre>Berisso</nombre>
		<personas>
			<persona>
				<nombre>Marina</nombre>
				<apellido>Lopez</apellido>
				<edad>25</edad>
			</persona>
			<persona>
				<nombre>Maria</nombre>
				<apellido>Gimenez</apellido>
				<edad>20</edad>
			</persona>	
			<persona>
				<nombre>Jose</nombre>
				<apellido>Trano</apellido>
				<edad>30</edad>
			</persona>
		</personas>
	</ciudad>
	<ciudad>
		<nombre>Ensenada</nombre>
		<personas>
			<persona>
				<nombre>Ariel</nombre>
				<apellido>Mango</apellido>
				<edad>18</edad>
			</persona>	
			<persona>
				<nombre>Ulises</nombre>
				<apellido>Prio</apellido>
				<edad>28</edad>
			</persona>	
			<persona>
				<nombre>Marta</nombre>
				<apellido>Perez</apellido>
				<edad>60</edad>
			</persona>
		</personas>
	</ciudad>			
</datos>
</xml> 